pyboot/commons/utils/antpath.py
pyboot/commons/utils/config.py
pyboot/commons/utils/file.py
pyboot/commons/utils/log.py
pyboot/commons/utils/reflect.py
pyboot/commons/utils/schedule.py
pyboot/commons/utils/sign.py
pyboot/commons/utils/thread.py
pyboot/commons/utils/utils.py
pyboot_commons_utils-1.3.3.dist-info/licenses/LICENSE
pyboot_commons_utils-1.3.3.dist-info/METADATA
pyboot_commons_utils-1.3.3.dist-info/WHEEL
pyboot_commons_utils-1.3.3.dist-info/top_level.txt
pyboot_commons_utils-1.3.3.dist-info/RECORD
